sslyzedb/__init__.py
sslyzedb/__main__.py
sslyzedb/utils.py
sslyzedb/core/__init__.py
sslyzedb/core/dbmodel.py
sslyzedb/core/report.py
sslyzedb/core/scanner.py
sslyzedb/core/utils.py
sslyzedb-0.0.2.dist-info/LICENSE
sslyzedb-0.0.2.dist-info/METADATA
sslyzedb-0.0.2.dist-info/WHEEL
sslyzedb-0.0.2.dist-info/entry_points.txt
sslyzedb-0.0.2.dist-info/top_level.txt
sslyzedb-0.0.2.dist-info/zip-safe
sslyzedb-0.0.2.dist-info/RECORD
