Metadata-Version: 2.1
Name: sslyzedb
Version: 0.0.2
Summary: DB driven SSLyze scanner
Home-page: https://github.com/skelsec/sslyzedb
Author: Tamas Jos
Author-email: info@skelsec.com
License: UNKNOWN
Platform: UNKNOWN
Classifier: Programming Language :: Python :: 3.6
Classifier: License :: OSI Approved :: MIT License
Classifier: Operating System :: OS Independent
Requires-Python: >=3.6
Requires-Dist: sslyze
Requires-Dist: sqlalchemy
Requires-Dist: tqdm
